cht_model_builder/__init__.py
cht_model_builder/model_builder.py
cht_model_builder-1.0.0.dist-info/LICENSE
cht_model_builder-1.0.0.dist-info/METADATA
cht_model_builder-1.0.0.dist-info/WHEEL
cht_model_builder-1.0.0.dist-info/top_level.txt
cht_model_builder-1.0.0.dist-info/RECORD
