Metadata-Version: 2.1
Name: cht_model_builder
Version: 1.0.0
Author-email: Maarten van Ormondt <maarten.vanormondt@deltares-usa.us>
Requires-Python: >=3.10
License-File: LICENSE
Requires-Dist: shapely
Requires-Dist: cht-bathymetry
Requires-Dist: cht-utils
